{
  "aircraft_id": "AC-1",
  "layout": {
    "business": {
      "rows": [1],
      "columns": ["A", "B", "C", "D"],
      "pattern": "2-2"
    },
    "economy": {
      "rows": [2],
      "columns": ["A", "B", "C", "D", "E", "F"],
      "pattern": "3-3"
    }
  },
  "seats": [
    {"seat_id": "1A", "cabin": "business", "seat_type": "window"},
    {"seat_id": "1B", "cabin": "business", "seat_type": "aisle"},
    {"seat_id": "1C", "cabin": "business", "seat_type": "aisle"},
    {"seat_id": "1D", "cabin": "business", "seat_type": "window"},
    {"seat_id": "2A", "cabin": "economy", "seat_type": "window"},
    {"seat_id": "2B", "cabin": "economy", "seat_type": "middle"},
    {"seat_id": "2C", "cabin": "economy", "seat_type": "aisle"},
    {"seat_id": "2D", "cabin": "economy", "seat_type": "aisle"},
    {"seat_id": "2E", "cabin": "economy", "seat_type": "middle"},
    {"seat_id": "2F", "cabin": "economy", "seat_type": "window"}
  ]
}
